<?xml version="1.0" encoding="UTF-8"?>
<list xmlns=""
      xmlns:ckbk="http://www.oreilly.com/xsltckbk"
      xmlns:pwl="http://papyri.uni-koeln.de/papyri-woerterlisten"
      xmlns:xi="http://www.w3.org/2001/XInclude"
      type="index"
      subtype="cat_abc_grc">
   <head>Einträge pro Kategorie und Initial (griechisch)</head>
   <item>
      <label type="general"/>
      <num>15211</num>
   </item>
   <item>
      <list type="index" subtype="general">
         <item>
            <label>Α</label>
            <num>2284</num>
         </item>
         <item>
            <label>-</label>
            <num>14</num>
         </item>
         <item>
            <label>Β</label>
            <num>325</num>
         </item>
         <item>
            <label>Γ</label>
            <num>278</num>
         </item>
         <item>
            <label>Δ</label>
            <num>822</num>
         </item>
         <item>
            <label>Ε</label>
            <num>2089</num>
         </item>
         <item>
            <label>Ζ</label>
            <num>96</num>
         </item>
         <item>
            <label>Η</label>
            <num>145</num>
         </item>
         <item>
            <label>Θ</label>
            <num>228</num>
         </item>
         <item>
            <label>Ι</label>
            <num>258</num>
         </item>
         <item>
            <label>Κ</label>
            <num>1515</num>
         </item>
         <item>
            <label>Λ</label>
            <num>423</num>
         </item>
         <item>
            <label>Μ</label>
            <num>683</num>
         </item>
         <item>
            <label>Ν</label>
            <num>169</num>
         </item>
         <item>
            <label>Ξ</label>
            <num>79</num>
         </item>
         <item>
            <label>Ο</label>
            <num>638</num>
         </item>
         <item>
            <label>Π</label>
            <num>1807</num>
         </item>
         <item>
            <label>Ρ</label>
            <num>114</num>
         </item>
         <item>
            <label>Σ</label>
            <num>1351</num>
         </item>
         <item>
            <label>(</label>
            <num>1</num>
         </item>
         <item>
            <label>Τ</label>
            <num>600</num>
         </item>
         <item>
            <label>Υ</label>
            <num>363</num>
         </item>
         <item>
            <label>Φ</label>
            <num>303</num>
         </item>
         <item>
            <label>Χ</label>
            <num>407</num>
         </item>
         <item>
            <label>Ψ</label>
            <num>71</num>
         </item>
         <item>
            <label>Ω</label>
            <num>61</num>
         </item>
         <item>
            <label>ϙ</label>
            <num>1</num>
         </item>
         <item>
            <label>]</label>
            <num>84</num>
         </item>
         <item>
            <label>[</label>
            <num>2</num>
         </item>
      </list>
   </item>
   <item>
      <label type="geography"/>
      <num>4681</num>
   </item>
   <item>
      <list type="index" subtype="geography">
         <item>
            <label>Α</label>
            <num>637</num>
         </item>
         <item>
            <label>Β</label>
            <num>142</num>
         </item>
         <item>
            <label>Γ</label>
            <num>52</num>
         </item>
         <item>
            <label>¥</label>
            <num>2</num>
         </item>
         <item>
            <label>Δ</label>
            <num>136</num>
         </item>
         <item>
            <label>Ε</label>
            <num>217</num>
         </item>
         <item>
            <label>Ζ</label>
            <num>19</num>
         </item>
         <item>
            <label>Η</label>
            <num>72</num>
         </item>
         <item>
            <label>Θ</label>
            <num>185</num>
         </item>
         <item>
            <label>Ι</label>
            <num>169</num>
         </item>
         <item>
            <label>Κ</label>
            <num>365</num>
         </item>
         <item>
            <label>Λ</label>
            <num>134</num>
         </item>
         <item>
            <label>Μ</label>
            <num>328</num>
         </item>
         <item>
            <label>Ν</label>
            <num>170</num>
         </item>
         <item>
            <label>Ξ</label>
            <num>13</num>
         </item>
         <item>
            <label>Ο</label>
            <num>98</num>
         </item>
         <item>
            <label>Π</label>
            <num>721</num>
         </item>
         <item>
            <label>Ρ</label>
            <num>25</num>
         </item>
         <item>
            <label>Σ</label>
            <num>357</num>
         </item>
         <item>
            <label>Τ</label>
            <num>414</num>
         </item>
         <item>
            <label>Υ</label>
            <num>10</num>
         </item>
         <item>
            <label>Φ</label>
            <num>168</num>
         </item>
         <item>
            <label>Χ</label>
            <num>95</num>
         </item>
         <item>
            <label>Ψ</label>
            <num>124</num>
         </item>
         <item>
            <label>Ω</label>
            <num>12</num>
         </item>
         <item>
            <label/>
            <num>1</num>
         </item>
         <item>
            <label>]</label>
            <num>10</num>
         </item>
         <item>
            <label>[</label>
            <num>5</num>
         </item>
      </list>
   </item>
   <item>
      <label type="persons"/>
      <num>14637</num>
   </item>
   <item>
      <list type="index" subtype="persons">
         <item>
            <label>Π</label>
            <num>2724</num>
         </item>
         <item>
            <label>Α</label>
            <num>2171</num>
         </item>
         <item>
            <label>Β</label>
            <num>342</num>
         </item>
         <item>
            <label>Γ</label>
            <num>154</num>
         </item>
         <item>
            <label>Δ</label>
            <num>386</num>
         </item>
         <item>
            <label>Ε</label>
            <num>654</num>
         </item>
         <item>
            <label>-</label>
            <num>4</num>
         </item>
         <item>
            <label>Ζ</label>
            <num>98</num>
         </item>
         <item>
            <label>Η</label>
            <num>177</num>
         </item>
         <item>
            <label>Θ</label>
            <num>509</num>
         </item>
         <item>
            <label>Ι</label>
            <num>370</num>
         </item>
         <item>
            <label>Κ</label>
            <num>1053</num>
         </item>
         <item>
            <label>Λ</label>
            <num>409</num>
         </item>
         <item>
            <label>Μ</label>
            <num>673</num>
         </item>
         <item>
            <label>Ν</label>
            <num>428</num>
         </item>
         <item>
            <label>Ξ</label>
            <num>26</num>
         </item>
         <item>
            <label>Ο</label>
            <num>376</num>
         </item>
         <item>
            <label>]</label>
            <num>75</num>
         </item>
         <item>
            <label>¥</label>
            <num>1</num>
         </item>
         <item>
            <label>Ρ</label>
            <num>87</num>
         </item>
         <item>
            <label>Σ</label>
            <num>1363</num>
         </item>
         <item>
            <label>Τ</label>
            <num>1258</num>
         </item>
         <item>
            <label>Υ</label>
            <num>40</num>
         </item>
         <item>
            <label>Φ</label>
            <num>446</num>
         </item>
         <item>
            <label>Χ</label>
            <num>295</num>
         </item>
         <item>
            <label>Ψ</label>
            <num>450</num>
         </item>
         <item>
            <label>Ω</label>
            <num>65</num>
         </item>
         <item>
            <label/>
            <num>3</num>
         </item>
      </list>
   </item>
   <item>
      <label type="monthsDays"/>
      <num>105</num>
   </item>
   <item>
      <list type="index" subtype="monthsDays">
         <item>
            <label>Α</label>
            <num>13</num>
         </item>
         <item>
            <label>Β</label>
            <num>3</num>
         </item>
         <item>
            <label>Γ</label>
            <num>4</num>
         </item>
         <item>
            <label>Δ</label>
            <num>11</num>
         </item>
         <item>
            <label>Ε</label>
            <num>5</num>
         </item>
         <item>
            <label>Ζ</label>
            <num>1</num>
         </item>
         <item>
            <label>Η</label>
            <num>1</num>
         </item>
         <item>
            <label>Θ</label>
            <num>5</num>
         </item>
         <item>
            <label>Ι</label>
            <num>3</num>
         </item>
         <item>
            <label>Κ</label>
            <num>4</num>
         </item>
         <item>
            <label>Λ</label>
            <num>1</num>
         </item>
         <item>
            <label>Μ</label>
            <num>5</num>
         </item>
         <item>
            <label>Ν</label>
            <num>8</num>
         </item>
         <item>
            <label>Ξ</label>
            <num>3</num>
         </item>
         <item>
            <label>Ο</label>
            <num>3</num>
         </item>
         <item>
            <label>Π</label>
            <num>11</num>
         </item>
         <item>
            <label>Ρ</label>
            <num>1</num>
         </item>
         <item>
            <label>Σ</label>
            <num>14</num>
         </item>
         <item>
            <label>Τ</label>
            <num>2</num>
         </item>
         <item>
            <label>Υ</label>
            <num>2</num>
         </item>
         <item>
            <label>Φ</label>
            <num>4</num>
         </item>
         <item>
            <label>Χ</label>
            <num>1</num>
         </item>
      </list>
   </item>
   <item>
      <label type="religion"/>
      <num>511</num>
   </item>
   <item>
      <list type="index" subtype="religion">
         <item>
            <label>Α</label>
            <num>102</num>
         </item>
         <item>
            <label>Β</label>
            <num>19</num>
         </item>
         <item>
            <label>Γ</label>
            <num>7</num>
         </item>
         <item>
            <label>Δ</label>
            <num>19</num>
         </item>
         <item>
            <label>Ε</label>
            <num>32</num>
         </item>
         <item>
            <label>Ζ</label>
            <num>10</num>
         </item>
         <item>
            <label>Η</label>
            <num>12</num>
         </item>
         <item>
            <label>Θ</label>
            <num>18</num>
         </item>
         <item>
            <label>Ι</label>
            <num>50</num>
         </item>
         <item>
            <label>Κ</label>
            <num>25</num>
         </item>
         <item>
            <label>Λ</label>
            <num>9</num>
         </item>
         <item>
            <label>Μ</label>
            <num>27</num>
         </item>
         <item>
            <label>Ν</label>
            <num>20</num>
         </item>
         <item>
            <label>Ο</label>
            <num>12</num>
         </item>
         <item>
            <label>Π</label>
            <num>30</num>
         </item>
         <item>
            <label>Ρ</label>
            <num>5</num>
         </item>
         <item>
            <label>Σ</label>
            <num>66</num>
         </item>
         <item>
            <label>Τ</label>
            <num>13</num>
         </item>
         <item>
            <label>Υ</label>
            <num>5</num>
         </item>
         <item>
            <label>Φ</label>
            <num>16</num>
         </item>
         <item>
            <label>Χ</label>
            <num>7</num>
         </item>
         <item>
            <label>Ω</label>
            <num>4</num>
         </item>
         <item>
            <label>]</label>
            <num>3</num>
         </item>
      </list>
   </item>
</list>
